{
  "basicInfo": {
    "assetNo": "CDCD::8475:1111:3900:2020",
    "assetType": "receivable",
    "assetName": "A电子技术有限公司-应收账款1",
    "assetOwner": "faa*****wxsl"
  },
  "detailedInfo": {
    "receivable":{
      "cargoName": "手机屏幕",
      "firstPaymentDate": "2019-10-01",
      "endPaymentDate": "2020-03-01",
      "lastPaymentDate":"2020-06-01",
      "allowOverdue": true,
      "overdueInterestRate": 0.05,
      "payerCode": "11050163030000000129",
      "payerName": "C科技有限公司",
      "paymentMethod": "现金/现汇",
      "receivableTotalAmount": 1350000.12,
      "currency": "CNY",
      "comments": "向C科技公司提供手机屏幕的应收账款"
    },
    "payments": [
      {
        "paymentDate": "2019-10-01",
        "amount": 200000,
        "stage": "已签合同"
      },
      {
        "paymentDate": "2019-12-01",
        "amount": 300000,
        "stage": "已交付"
      }
    ],
    "contracts": [
      {
        "contractNo": "444b5cc0-ae5d-11e6-8d22-28924a431726",
        "originalContractNo": "HT20190403021",
        "contractName": "手机屏幕采购合同",
        "contractType": "购销合同",
        "payerCode": "91350100M000100Y43",
        "payerName": "C科技有限公司",
        "payerBankName": "建设银行上海张江支行",
        "payerBankAccount": "11050163030000000129",
        "receiverCode": "52100000523000026F",
        "receiverName": "A电子技术有限公司",
        "receiverBankName": "农业银行北京清河支行",
        "receiverBankAccount": "11250201040018302",
        "contractAmount": 1850000.12,
        "currency": "CNY",
        "contractDate": "2019-03-15",
        "contractAttachment": "https://aliyun/contractStorageURL"
      }
    ],
    "invoices":[
      {
        "invoiceNo": "31897346",
        "invoiceDate": "2019-09-15",
        "invoiceAmount": 200000,
        "currency": "CNY",
        "payerCode": "91350100M000100Y43",
        "payerName": "C科技有限公司",
        "receiverCode": "52100000523000026F",
        "receiverName": "A电子技术有限公司",
        "invoiceAttachment":  "https://aliyun/invoiceStorageURL1"
      },
      {
        "invoiceNo": "73463189",
        "invoiceDate": "2019-11-15",
        "invoiceAmount": 300000,
        "currency": "CNY",
        "payerCode": "91350100M000100Y43",
        "payerName": "C科技有限公司",
        "receiverCode": "52100000523000026F",
        "receiverName": "A电子技术有限公司",
        "invoiceAttachment": "https://aliyun/invoiceStorageURL2"
      }
    ]
  }
}